{"id":985,"date":"2010-01-19T07:55:35","date_gmt":"2010-01-18T23:55:35","guid":{"rendered":"http://xbeta.info/?p=985"},"modified":"2010-01-19T07:55:35","modified_gmt":"2010-01-18T23:55:35","slug":"software-price","status":"publish","link":"https://xbeta.info/software-price.htm","title":{"rendered":"[讨论] 中国的软件价格是否太贵？"},"content":{"rendered":"<p>共享软件的价格多少才合适？定价要与作者的付出相比，还是与读者的收益相比，还是与其他软件相比？Dexter网友来信谈TC的价格，经其同意，发于此，请大家一起讨论。我后须也会补上自己的观点。（另：请大家反馈一下 <a href=\"http://xbeta.info/studytc/\">TC学堂的首页链接</a> 访问正常否？注意清空缓存。）</p>\n<blockquote><p>\n　　看了你做的tc方面的教程后对tc的确有了购买的想法，可我去了解下来发现真要买还真是有很大的阻力</p>\n<p>　　首先是价格，虽然我不知道具体26欧元具体值多少人民币，可估摸着250应该要的吧，理智的讲站在消费者的立场上是不能接受的，要知道新蛋，京东上的正版xp是299，正版win7是399，一个tc的售价几乎接近于一个操作系统的价格，我想问您，您觉得这合理吗</p>\n<p>　　我知道可能对于作者来说以他的生活水平这个价格的确是不贵，可我们生活在中国，这还真不一样，说点现实点的例子，同样是国外软件，卡巴斯基在中国可以说取得了很大的成功，我看新闻说它在中国收入上亿，广告都做到cctv上了，当然了这也有360推广的因素，可卡巴斯基一年几十元的售价作为他在中国成功的前提条件是功不可没的，如果他也卖个200-300百，他可能会在中国那么成功吗?如果您能说服作者降价到合理的价位，对于推广tc比您多写n篇tc的教程更有力，我也不是很斤斤计较的人，像我买mybase对其价格没任何想法，当然了可能作者是中国人的关系他了解国情，所以开价很合理</p>\n<p>　　其次是购买方式，我看过你说的4个途径，不管哪个购买途径对于国人来说是难了点</p>\n<p>　　我建议您和作者沟通下，让你做tc的中国区的代理，您可以通过支付宝这个平台来出售，这样相对的来说也杜绝了发达国家的用户来买便宜的tc让作者受到损失而且让国人购买方便些</p>\n<p>　　我贴下新蛋上面的各知名软件的价格链接，希望能让作者了解下中国的国情<br />\n　　http://www.newegg.com.cn/Product/62-c88-099.htm   卡巴斯基3年 139<br />\n　　http://www.newegg.com.cn/Product/50-c04-012.htm   xp 299<br />\n　　http://www.newegg.com.cn/Product/62-c88-031.htm   win7 399<br />\n　　http://www.newegg.com.cn/Product/62-c88-029.htm   诺顿3用户2年 108<br />\n　　http://www.newegg.com.cn/Product/62-c88-014.htm   office 199</p></blockquote>\n<p></iframe></p>\n","protected":false},"excerpt":{"rendered":"<p>共享软件的价格多少才合适？定价要与作者的付出相比，还是与读者的收益相比，还是与其他软件相比？Dexter网友来 [&hellip;]</p>\n","protected":false},"author":2,"featured_media":0,"comment_status":"open","ping_status":"open","sticky":false,"template":"","format":"standard","meta":[],"categories":["未分类"],"tags":["all"],"_links":{"self":[{"href":"https://xbeta.info/wp-json/wp/v2/posts/985"}],"collection":[{"href":"https://xbeta.info/wp-json/wp/v2/posts"}],"about":[{"href":"https://xbeta.info/wp-json/wp/v2/types/post"}],"author":[{"embeddable":true,"href":"https://xbeta.info/wp-json/wp/v2/users/2"}],"replies":[{"embeddable":true,"href":"https://xbeta.info/wp-json/wp/v2/comments?post=985"}],"version-history":[{"count":0,"href":"https://xbeta.info/wp-json/wp/v2/posts/985/revisions"}],"wp:attachment":[{"href":"https://xbeta.info/wp-json/wp/v2/media?parent=985"}],"wp:term":[{"taxonomy":"category","embeddable":true,"href":"https://xbeta.info/wp-json/wp/v2/categories?post=985"},{"taxonomy":"post_tag","embeddable":true,"href":"https://xbeta.info/wp-json/wp/v2/tags?post=985"}],"curies":[{"name":"wp","href":"https://api.w.org/{rel}","templated":true}]},"wp_type":"post"}